image_label/__init__.py
image_label/frontend/build/asset-manifest.json
image_label/frontend/build/bootstrap.min.css
image_label/frontend/build/index.html
image_label/frontend/build/static/css/main.38c3892c.chunk.css
image_label/frontend/build/static/css/main.38c3892c.chunk.css.map
image_label/frontend/build/static/js/2.d663ce47.chunk.js
image_label/frontend/build/static/js/2.d663ce47.chunk.js.LICENSE.txt
image_label/frontend/build/static/js/2.d663ce47.chunk.js.map
image_label/frontend/build/static/js/main.c0d60b13.chunk.js
image_label/frontend/build/static/js/main.c0d60b13.chunk.js.map
image_label/frontend/build/static/js/runtime-main.657b0728.js
image_label/frontend/build/static/js/runtime-main.657b0728.js.map
image_label/frontend/build/static/media/expand.9dd54df5.svg
image_label/frontend/build/static/media/shrink.38fe5d9e.svg
image_label-2.4.3.dist-info/LICENSE
image_label-2.4.3.dist-info/METADATA
image_label-2.4.3.dist-info/WHEEL
image_label-2.4.3.dist-info/top_level.txt
image_label-2.4.3.dist-info/RECORD
