Metadata-Version: 2.1
Name: image-label
Version: 2.4.3
Summary: This is an Image Labeling Component for streamlit
Home-page: https://github.com/SksOp/image_label
Author: sks
Author-email: shubhaman47@gmail.com
Requires-Python: >=3.6
License-File: LICENSE
Requires-Dist: streamlit (>=0.63)
